LICENSE
README.rst
setup.cfg
setup.py
src/mke_client/__init__.py
src/mke_client/helpers.py
src/mke_client/obs_scheduling.py
src/mke_client/remexlib.py
src/mke_client/rimlib.py
src/mke_client/runlib.py
src/mke_client.egg-info/PKG-INFO
src/mke_client.egg-info/SOURCES.txt
src/mke_client.egg-info/dependency_links.txt
src/mke_client.egg-info/top_level.txt