Metadata-Version: 2.1
Name: mke-client
Version: 2.0.0
Summary: MeerKAT Extension (MKE) (r)emote (i)nterface (m)anagement (lib)rary
Home-page: https://github.com/TobiasGlaubach/mke_clientlib
Author: Tobias Glaubach
Author-email: tglaubach@mpifr-bonn.mpg.de
License: UNKNOWN
Project-URL: Bug Tracker, https://github.com/TobiasGlaubach/mke_clientlib/issues
Platform: UNKNOWN
Classifier: License :: OSI Approved :: GNU General Public License v3 or later (GPLv3+)
Classifier: Operating System :: OS Independent
Classifier: Environment :: Console
Classifier: Programming Language :: Python
Classifier: Programming Language :: Python :: 3
Classifier: Programming Language :: Python :: 3 :: Only
Requires-Python: >=3.8
License-File: LICENSE
